jakarto_datasets/__init__.py
jakarto_datasets/commons/__init__.py
jakarto_datasets/commons/path_manager.py
jakarto_datasets/datasets/__init__.py
jakarto_datasets/datasets/storm_drains/__init__.py
jakarto_datasets/datasets/storm_drains/storm_drains.py
jakarto_datasets/utils/__init__.py
jakarto_datasets/utils/archive_manager.py
jakarto_datasets/utils/data_structure_operator.py
jakarto_datasets/utils/downloader.py
jakarto_datasets/utils/memory_manager.py
jakarto_datasets-0.1.0.dist-info/LICENSE.txt
jakarto_datasets-0.1.0.dist-info/METADATA
jakarto_datasets-0.1.0.dist-info/WHEEL
jakarto_datasets-0.1.0.dist-info/top_level.txt
jakarto_datasets-0.1.0.dist-info/RECORD
