Metadata-Version: 2.1
Name: jakarto-datasets
Version: 0.1.0
Summary: Jakarto datasets containing realworld 3d data from lidar sensors.
Home-page: https://github.com/jakarto3d/jakarto_datasets
Author: Loïc Messal
Author-email: loic.messal@jakarto.com
License: MIT License
Platform: UNKNOWN
Classifier: Programming Language :: Python :: 3
Classifier: License :: OSI Approved :: MIT License
Classifier: Operating System :: OS Independent
Requires-Python: >=3.6
Requires-Dist: numpy
Requires-Dist: imageio
Requires-Dist: laspy
Requires-Dist: tqdm
